ebuild_util/__init__.py
ebuild_util/ebuild.py
ebuild_util-1.0.3.dist-info/DESCRIPTION.rst
ebuild_util-1.0.3.dist-info/METADATA
ebuild_util-1.0.3.dist-info/RECORD
ebuild_util-1.0.3.dist-info/WHEEL
ebuild_util-1.0.3.dist-info/metadata.json
ebuild_util-1.0.3.dist-info/top_level.txt
