Metadata-Version: 2.0
Name: ebuild-util
Version: 1.0.3
Summary: Utilities for ebuild files
Home-page: https://github.com/nicholasbishop/ebuild_util
Author: Nicholas Bishop
Author-email: nicholasbishop@gmail.com
License: Apache 2.0
Platform: UNKNOWN
Requires-Dist: attrs (>=17.0.0)
Requires-Dist: numeric-version (>=1.0.3)
